README.md
setup.py
mysqltools/__init__.py
mysqltools/mysql_connection.py
mysqltools/sql_read.py
mysqltools/sql_store.py
mysqltools.egg-info/PKG-INFO
mysqltools.egg-info/SOURCES.txt
mysqltools.egg-info/dependency_links.txt
mysqltools.egg-info/top_level.txt