Metadata-Version: 2.1
Name: mysqltools
Version: 0.0.1
Summary: mysql aggregated tools for our own
Home-page: UNKNOWN
Author: zuel_quant_lab
Author-email: kiway_d@163.com
License: UNKNOWN
Platform: UNKNOWN
Classifier: Programming Language :: Python :: 3
Classifier: License :: OSI Approved :: MIT License
Classifier: Operating System :: OS Independent
Requires-Python: >=3.8
